tkwidgets/__init__.py
tkwidgets/checkbox.py
tkwidgets/date_dropdown.py
tkwidgets/joystick.py
tkwidgets/progressbar.py
tkwidgets/scrollbar.py
tkwidgets/skillweb.py
tkwidgets/tile_map.py
tkwidgets-0.3.2.dist-info/licenses/LICENSE
tkwidgets-0.3.2.dist-info/METADATA
tkwidgets-0.3.2.dist-info/WHEEL
tkwidgets-0.3.2.dist-info/top_level.txt
tkwidgets-0.3.2.dist-info/RECORD
